arsein/Arsein.py
arsein/Clien.py
arsein/Copyright.py
arsein/Device.py
arsein/Encoder.py
arsein/Error.py
arsein/Getheader.py
arsein/GtM.py
arsein/PostData.py
arsein/TypeText.py
arsein/Zedcontent.py
arsein/__init__.py
ArseinTest-4.8.8.dist-info/LICENCE
ArseinTest-4.8.8.dist-info/METADATA
ArseinTest-4.8.8.dist-info/WHEEL
ArseinTest-4.8.8.dist-info/top_level.txt
ArseinTest-4.8.8.dist-info/RECORD
