Metadata-Version: 2.1
Name: ArseinTest
Version: 4.8.8
Summary: library Robot Rubika
Home-page: https://github.com/Arseinlibrary/Arsein__library.git
Author: arian abasi nedamane
Author-email: aryongram@gmail.com
License: MIT
Keywords: Arsein,Arseinrubika,ArseinRubika,arsein,bot,Bot,BOT,Robot,ROBOT,robot,self,api,API,Api,rubika,Rubika,RUBIKA,Python,python,aiohttp,asyncio
Classifier: Development Status :: 3 - Alpha
Classifier: Intended Audience :: Developers
Classifier: Topic :: Software Development :: Build Tools
Classifier: License :: OSI Approved :: MIT License
Classifier: Programming Language :: Python :: Implementation :: PyPy
Classifier: Programming Language :: Python :: 3
Classifier: Programming Language :: Python :: 3.4
Classifier: Programming Language :: Python :: 3.5
Classifier: Programming Language :: Python :: 3.6
Classifier: Programming Language :: Python :: 3.7
Classifier: Programming Language :: Python :: 3.8
Classifier: Programming Language :: Python :: 3.9
Classifier: Programming Language :: Python :: 3.10
Classifier: Programming Language :: Python :: 3.11
License-File: LICENCE
Requires-Dist: pycryptodome (==3.16.0)
Requires-Dist: aiohttp (==3.8.3)
Requires-Dist: asyncio (==3.4.3)
Requires-Dist: tinytag (==1.8.1)
Requires-Dist: Pillow (==9.4.0)
